toktkn-0.1.2.dist-info/METADATA
toktkn-0.1.2.dist-info/WHEEL
toktkn.libs/libgcc_s-1e52349c.so.1
toktkn/__init__.py
toktkn/toktkn.abi3.so
toktkn-0.1.2.dist-info/RECORD
