Metadata-Version: 2.4
Name: toktkn
Version: 0.1.2
Summary: a minimal byte-pair encoding tokenizer implementation
Keywords: nlp,python,maturin,pyo3
Home-Page: https://github.com/nnethercott/toktkn
License: MIT
Project-URL: Source Code, https://github.com/nnethercott/toktkn
